jsonpatch2pymongo/__init__.py
jsonpatch2pymongo/main.py
jsonpatch2pymongo/version.py
jsonpatch2pymongo-0.1.3.dist-info/METADATA
jsonpatch2pymongo-0.1.3.dist-info/WHEEL
jsonpatch2pymongo-0.1.3.dist-info/licenses/LICENSE
jsonpatch2pymongo-0.1.3.dist-info/RECORD
